pye57/__init__.py
pye57/__version__.py
pye57/e57.py
pye57/exception.py
pye57/libe57.cp39-win_amd64.pyd
pye57/scan_header.py
pye57/utils.py
pye57/xerces-c_3_2.dll
pye57-0.4.18.dist-info/licenses/LICENSE
pye57-0.4.18.dist-info/METADATA
pye57-0.4.18.dist-info/WHEEL
pye57-0.4.18.dist-info/top_level.txt
pye57-0.4.18.dist-info/RECORD
